baikal/language/__init__.py
baikal/language/custom_dict_pb2.py
baikal/language/custom_dict_pb2.pyi
baikal/language/custom_dict_pb2_grpc.py
baikal/language/custom_dict_pb2_grpc.pyi
baikal/language/dict_common_pb2.py
baikal/language/dict_common_pb2.pyi
baikal/language/language_service_pb2.py
baikal/language/language_service_pb2.pyi
baikal/language/language_service_pb2_grpc.py
baikal/language/language_service_pb2_grpc.pyi
baikalai_apis-0.9.1.dist-info/LICENSE
baikalai_apis-0.9.1.dist-info/WHEEL
baikalai_apis-0.9.1.dist-info/METADATA
baikalai_apis-0.9.1.dist-info/RECORD
